{"chartTitle":"Trend over 1990 - 2019","nomPaysUk":"swaziland","trade":true,"stackType":"none","nameSerie":"Electricity balance of trade","chartData":"[{annee: 1990,'171': 0.39},{annee: 1991,'171': 0.35},{annee: 1992,'171': 0.57},{annee: 1993,'171': 0.53},{annee: 1994,'171': 0.58},{annee: 1995,'171': 0.62},{annee: 1996,'171': 0.57},{annee: 1997,'171': 0.61},{annee: 1998,'171': 0.69},{annee: 1999,'171': 0.70},{annee: 2000,'171': 0.70},{annee: 2001,'171': 0.64},{annee: 2002,'171': 0.80},{annee: 2003,'171': 0.80},{annee: 2004,'171': 0.70},{annee: 2005,'171': 0.87},{annee: 2006,'171': 0.76},{annee: 2007,'171': 0.94},{annee: 2008,'171': 0.98},{annee: 2009,'171': 0.92},{annee: 2010,'171': 0.91},{annee: 2011,'171': 0.81},{annee: 2012,'171': 0.81},{annee: 2013,'171': 0.82},{annee: 2014,'171': 0.86},{annee: 2015,'171': 0.98},{annee: 2016,'171': 1.08},{annee: 2017,'171': 1.05},{annee: 2018,'171': 1.02},{annee: 2019,forceShow: true}]","valueAxisMinimum":0,"color":"#00758F","tabGraphs":[{"valueField":"171","nameGraph":"Swaziland","unit":" TWh","fillColors":"#004a5b","lineColor":"#004a5b","type":"column","lineAlpha":0,"fillAlphas":1,"balloonText":"Swaziland [[category]]: [[value]] TWh"}],"yearRange":true,"idDiv":"graph","anneeMin":1990,"anneeMax":2019,"paysGraph":"<b>Selected countries:<\/b>","codeISOPaysChoisi":"SZ","countryTitle":"Swaziland","categoryAxis":{"gridPosition":"start"},"nbPaysBenchmark":0,"serie":{"id":"785","code":"elexm","nomFr":"Solde du commerce ext\u00e9rieur \u00e9lectricit\u00e9","nomUk":"Electricity balance of trade","nom":"Electricity balance of trade","titreCourt":"Electricity balance of trade","idService":"1","calcul":false}}