{"chartTitle":"Trend over 1990 - 2019","nomPaysUk":"zimbabwe","trade":true,"stackType":"none","nameSerie":"Electricity balance of trade","chartData":"[{annee: 1990,'176': 0.33},{annee: 1991,'176': 1.14},{annee: 1992,'176': 2.03},{annee: 1993,'176': 1.21},{annee: 1994,'176': 2.01},{annee: 1995,'176': 2.32},{annee: 1996,'176': 3.15},{annee: 1997,'176': 4.01},{annee: 1998,'176': 4.92},{annee: 1999,'176': 5.28},{annee: 2000,'176': 5.10},{annee: 2001,'176': 4.07},{annee: 2002,'176': 4.01},{annee: 2003,'176': 3.19},{annee: 2004,'176': 2.04},{annee: 2005,'176': 2.98},{annee: 2006,'176': 3.90},{annee: 2007,'176': 2.93},{annee: 2008,'176': 1.12},{annee: 2009,'176': 1.28},{annee: 2010,'176': 0.73},{annee: 2011,'176': 0.60},{annee: 2012,'176': 0.55},{annee: 2013,'176': 0.53},{annee: 2014,'176': -0.10},{annee: 2015,'176': -0.10},{annee: 2016,'176': 1.85},{annee: 2017,'176': 2.22},{annee: 2018,'176': 1.11},{annee: 2019,forceShow: true}]","valueAxisMinimum":"auto","color":"#00758F","tabGraphs":[{"valueField":"176","nameGraph":"Zimbabwe","unit":" TWh","fillColors":"#004a5b","lineColor":"#004a5b","type":"column","lineAlpha":0,"fillAlphas":1,"balloonText":"Zimbabwe [[category]]: [[value]] TWh"}],"yearRange":true,"idDiv":"graph","anneeMin":1990,"anneeMax":2019,"paysGraph":"<b>Selected countries:<\/b>","codeISOPaysChoisi":"ZW","countryTitle":"Zimbabwe","categoryAxis":{"gridPosition":"start"},"nbPaysBenchmark":0,"serie":{"id":"785","code":"elexm","nomFr":"Solde du commerce ext\u00e9rieur \u00e9lectricit\u00e9","nomUk":"Electricity balance of trade","nom":"Electricity balance of trade","titreCourt":"Electricity balance of trade","idService":"1","calcul":false}}